Workbook

Sheet Instrucciones
A1: Facturación en ARCA — planilla por emisor
A2: Una planilla por cada persona que factura. Una hoja por mes.
A4: Cómo se usa
A5: 1. | B5: Completar una sola vez la hoja 'Emisor' con los datos de quien factura.
A6: 2. | B6: Cargar los clientes en la hoja 'Clientes' (una sola vez; agregar los nuevos cuando aparezcan).
A7: 3. | B7: Cada mes: copiar la hoja 'Plantilla', renombrarla con el mes (ej. 'Octubre 2026') y completar una fila por factura.
A8: 4. | B8: Al emitir en ARCA se completan las columnas grises (N° de comprobante y ¿Emitida?).
A10: Colores
A11: Amarillo | B11: Lo completa quien pide la factura
A12: Gris | B12: Se completa al emitir en ARCA
A13: Blanco | B13: Se calcula solo; no tocar
A15: Tipo de factura
A16: Monotributo | B16: Siempre Factura C. No se discrimina IVA: el importe es el total.
A17: Resp. Inscripto | B17: Factura A a clientes Resp. Inscriptos o Monotributistas; Factura B al resto. Se carga el importe neto y la planilla calcula IVA y total.
A19: Ejemplo de fila (solo referencia)
A20: CUIT cliente | B20: 30712345678
A21: Descripción | B21: Honorarios Profesionales Octubre 2026
A22: Importe neto | B22: $ 450.000 (valor inventado)
A23: Fechas | B23: Factura 31/10/2026 · Período 01/10/2026 al 31/10/2026 · Vto. 06/11/2026
A24: Condición de venta | B24: Transferencia Bancaria

Sheet Emisor
A1: Datos del emisor
A2: Completar una sola vez. Nunca anotar la clave fiscal en esta planilla.
A5: Nombre (como figura en ARCA)
A6: CUIT
A7: Condición frente al IVA | C7: Responsable Monotributo o IVA Responsable Inscripto
A8: Punto de venta | C8: Ej. 1 (se ve en el historial de comprobantes)
A9: Actividad asociada (código) | C9: Ej. 692000
A10: Alícuota de IVA habitual | C10: Solo Resp. Inscripto. Ej. 21%
A11: Carpeta donde guardar los PDF | C11: Opcional

Sheet Clientes
A1: Clientes
A2: Una fila por cliente. Completar una sola vez.
A4: CUIT | B4: Razón social | C4: Condición frente al IVA | D4: Descripción habitual | E4: Condición de venta habitual | F4: ¿Sigue activo? | G4: Notas

Sheet Plantilla
A1: Facturas a emitir — [MES AAAA]
A2: Copiar esta hoja para cada mes. Una fila por factura.
A4: CUIT cliente | B4: Razón social (automático) | C4: Condición IVA (automático) | D4: Tipo de factura (automático) | E4: Descripción del servicio | F4: Importe neto ($) | G4: IVA ($) (automático) | H4: Total ($) (automático) | I4: Fecha de la factura | J4: Período desde | K4: Período hasta | L4: Vencimiento de pago | M4: Condición de venta | N4: Observaciones | O4: N° comprobante | P4: ¿Emitida?
B5: =IF(A5="","",IFERROR(INDEX(Clientes!$B$5:$B$60,MATCH(A5,Clientes!$A$5:$A$60,0)),"CUIT no cargado en Clientes")) | C5: =IF(A5="","",IFERROR(INDEX(Clientes!$C$5:$C$60,MATCH(A5,Clientes!$A$5:$A$60,0)),"")) | D5: =IF(A5="","",IF(Emisor!$B$7="Responsable Monotributo","Factura C",IF(OR(C5="IVA Responsable Inscripto",C5="Responsable Monotributo"),"Factura A","Factura B"))) | G5: =IF(F5="","",IF(Emisor!$B$7="IVA Responsable Inscripto",ROUND(F5*Emisor!$B$10,2),0)) | H5: =IF(F5="","",F5+G5)
B6: =IF(A6="","",IFERROR(INDEX(Clientes!$B$5:$B$60,MATCH(A6,Clientes!$A$5:$A$60,0)),"CUIT no cargado en Clientes")) | C6: =IF(A6="","",IFERROR(INDEX(Clientes!$C$5:$C$60,MATCH(A6,Clientes!$A$5:$A$60,0)),"")) | D6: =IF(A6="","",IF(Emisor!$B$7="Responsable Monotributo","Factura C",IF(OR(C6="IVA Responsable Inscripto",C6="Responsable Monotributo"),"Factura A","Factura B"))) | G6: =IF(F6="","",IF(Emisor!$B$7="IVA Responsable Inscripto",ROUND(F6*Emisor!$B$10,2),0)) | H6: =IF(F6="","",F6+G6)
B7: =IF(A7="","",IFERROR(INDEX(Clientes!$B$5:$B$60,MATCH(A7,Clientes!$A$5:$A$60,0)),"CUIT no cargado en Clientes")) | C7: =IF(A7="","",IFERROR(INDEX(Clientes!$C$5:$C$60,MATCH(A7,Clientes!$A$5:$A$60,0)),"")) | D7: =IF(A7="","",IF(Emisor!$B$7="Responsable Monotributo","Factura C",IF(OR(C7="IVA Responsable Inscripto",C7="Responsable Monotributo"),"Factura A","Factura B"))) | G7: =IF(F7="","",IF(Emisor!$B$7="IVA Responsable Inscripto",ROUND(F7*Emisor!$B$10,2),0)) | H7: =IF(F7="","",F7+G7)
B8: =IF(A8="","",IFERROR(INDEX(Clientes!$B$5:$B$60,MATCH(A8,Clientes!$A$5:$A$60,0)),"CUIT no cargado en Clientes")) | C8: =IF(A8="","",IFERROR(INDEX(Clientes!$C$5:$C$60,MATCH(A8,Clientes!$A$5:$A$60,0)),"")) | D8: =IF(A8="","",IF(Emisor!$B$7="Responsable Monotributo","Factura C",IF(OR(C8="IVA Responsable Inscripto",C8="Responsable Monotributo"),"Factura A","Factura B"))) | G8: =IF(F8="","",IF(Emisor!$B$7="IVA Responsable Inscripto",ROUND(F8*Emisor!$B$10,2),0)) | H8: =IF(F8="","",F8+G8)
B9: =IF(A9="","",IFERROR(INDEX(Clientes!$B$5:$B$60,MATCH(A9,Clientes!$A$5:$A$60,0)),"CUIT no cargado en Clientes")) | C9: =IF(A9="","",IFERROR(INDEX(Clientes!$C$5:$C$60,MATCH(A9,Clientes!$A$5:$A$60,0)),"")) | D9: =IF(A9="","",IF(Emisor!$B$7="Responsable Monotributo","Factura C",IF(OR(C9="IVA Responsable Inscripto",C9="Responsable Monotributo"),"Factura A","Factura B"))) | G9: =IF(F9="","",IF(Emisor!$B$7="IVA Responsable Inscripto",ROUND(F9*Emisor!$B$10,2),0)) | H9: =IF(F9="","",F9+G9)
B10: =IF(A10="","",IFERROR(INDEX(Clientes!$B$5:$B$60,MATCH(A10,Clientes!$A$5:$A$60,0)),"CUIT no cargado en Clientes")) | C10: =IF(A10="","",IFERROR(INDEX(Clientes!$C$5:$C$60,MATCH(A10,Clientes!$A$5:$A$60,0)),"")) | D10: =IF(A10="","",IF(Emisor!$B$7="Responsable Monotributo","Factura C",IF(OR(C10="IVA Responsable Inscripto",C10="Responsable Monotributo"),"Factura A","Factura B"))) | G10: =IF(F10="","",IF(Emisor!$B$7="IVA Responsable Inscripto",ROUND(F10*Emisor!$B$10,2),0)) | H10: =IF(F10="","",F10+G10)
B11: =IF(A11="","",IFERROR(INDEX(Clientes!$B$5:$B$60,MATCH(A11,Clientes!$A$5:$A$60,0)),"CUIT no cargado en Clientes")) | C11: =IF(A11="","",IFERROR(INDEX(Clientes!$C$5:$C$60,MATCH(A11,Clientes!$A$5:$A$60,0)),"")) | D11: =IF(A11="","",IF(Emisor!$B$7="Responsable Monotributo","Factura C",IF(OR(C11="IVA Responsable Inscripto",C11="Responsable Monotributo"),"Factura A","Factura B"))) | G11: =IF(F11="","",IF(Emisor!$B$7="IVA Responsable Inscripto",ROUND(F11*Emisor!$B$10,2),0)) | H11: =IF(F11="","",F11+G11)
B12: =IF(A12="","",IFERROR(INDEX(Clientes!$B$5:$B$60,MATCH(A12,Clientes!$A$5:$A$60,0)),"CUIT no cargado en Clientes")) | C12: =IF(A12="","",IFERROR(INDEX(Clientes!$C$5:$C$60,MATCH(A12,Clientes!$A$5:$A$60,0)),"")) | D12: =IF(A12="","",IF(Emisor!$B$7="Responsable Monotributo","Factura C",IF(OR(C12="IVA Responsable Inscripto",C12="Responsable Monotributo"),"Factura A","Factura B"))) | G12: =IF(F12="","",IF(Emisor!$B$7="IVA Responsable Inscripto",ROUND(F12*Emisor!$B$10,2),0)) | H12: =IF(F12="","",F12+G12)
B13: =IF(A13="","",IFERROR(INDEX(Clientes!$B$5:$B$60,MATCH(A13,Clientes!$A$5:$A$60,0)),"CUIT no cargado en Clientes")) | C13: =IF(A13="","",IFERROR(INDEX(Clientes!$C$5:$C$60,MATCH(A13,Clientes!$A$5:$A$60,0)),"")) | D13: =IF(A13="","",IF(Emisor!$B$7="Responsable Monotributo","Factura C",IF(OR(C13="IVA Responsable Inscripto",C13="Responsable Monotributo"),"Factura A","Factura B"))) | G13: =IF(F13="","",IF(Emisor!$B$7="IVA Responsable Inscripto",ROUND(F13*Emisor!$B$10,2),0)) | H13: =IF(F13="","",F13+G13)
B14: =IF(A14="","",IFERROR(INDEX(Clientes!$B$5:$B$60,MATCH(A14,Clientes!$A$5:$A$60,0)),"CUIT no cargado en Clientes")) | C14: =IF(A14="","",IFERROR(INDEX(Clientes!$C$5:$C$60,MATCH(A14,Clientes!$A$5:$A$60,0)),"")) | D14: =IF(A14="","",IF(Emisor!$B$7="Responsable Monotributo","Factura C",IF(OR(C14="IVA Responsable Inscripto",C14="Responsable Monotributo"),"Factura A","Factura B"))) | G14: =IF(F14="","",IF(Emisor!$B$7="IVA Responsable Inscripto",ROUND(F14*Emisor!$B$10,2),0)) | H14: =IF(F14="","",F14+G14)
B15: =IF(A15="","",IFERROR(INDEX(Clientes!$B$5:$B$60,MATCH(A15,Clientes!$A$5:$A$60,0)),"CUIT no cargado en Clientes")) | C15: =IF(A15="","",IFERROR(INDEX(Clientes!$C$5:$C$60,MATCH(A15,Clientes!$A$5:$A$60,0)),"")) | D15: =IF(A15="","",IF(Emisor!$B$7="Responsable Monotributo","Factura C",IF(OR(C15="IVA Responsable Inscripto",C15="Responsable Monotributo"),"Factura A","Factura B"))) | G15: =IF(F15="","",IF(Emisor!$B$7="IVA Responsable Inscripto",ROUND(F15*Emisor!$B$10,2),0)) | H15: =IF(F15="","",F15+G15)
B16: =IF(A16="","",IFERROR(INDEX(Clientes!$B$5:$B$60,MATCH(A16,Clientes!$A$5:$A$60,0)),"CUIT no cargado en Clientes")) | C16: =IF(A16="","",IFERROR(INDEX(Clientes!$C$5:$C$60,MATCH(A16,Clientes!$A$5:$A$60,0)),"")) | D16: =IF(A16="","",IF(Emisor!$B$7="Responsable Monotributo","Factura C",IF(OR(C16="IVA Responsable Inscripto",C16="Responsable Monotributo"),"Factura A","Factura B"))) | G16: =IF(F16="","",IF(Emisor!$B$7="IVA Responsable Inscripto",ROUND(F16*Emisor!$B$10,2),0)) | H16: =IF(F16="","",F16+G16)
... B24: =IF(A24="","",IFERROR(INDEX(Clientes!$B$5:$B$60,MATCH(A24,Clientes!$A$5:$A$60,0)),"CUIT no cargado en Clientes")) | C24: =IF(A24="","",IFERROR(INDEX(Clientes!$C$5:$C$60,MATCH(A24,Clientes!$A$5:$A$60,0)),"")) | D24: =IF(A24="","",IF(Emisor!$B$7="Responsable Monotributo","Factura C",IF(OR(C24="IVA Responsable Inscripto",C24="Responsable Monotributo"),"Factura A","Factura B"))) | G24: =IF(F24="","",IF(Emisor!$B$7="IVA Responsable Inscripto",ROUND(F24*Emisor!$B$10,2),0)) | H24: =IF(F24="","",F24+G24)
E25: TOTAL | H25: =SUM(H5:H24) -> 0
E26: Facturas cargadas | H26: =COUNTIF(A5:A24,"?*") -> 0
E27: Facturas emitidas | H27: =COUNTIF(P5:P24,"Sí") -> 0
